forge/__init__.py
forge/cleanup.py
forge/common.py
forge/configuration.py
forge/configure.py
forge/create.py
forge/destroy.py
forge/engine.py
forge/exceptions.py
forge/main.py
forge/parser.py
forge/rsync.py
forge/run.py
forge/ssh.py
forge/start.py
forge/stop.py
cars_forge-1.3.5.dist-info/METADATA
cars_forge-1.3.5.dist-info/WHEEL
cars_forge-1.3.5.dist-info/entry_points.txt
cars_forge-1.3.5.dist-info/licenses/LICENSE
cars_forge-1.3.5.dist-info/RECORD
