Metadata-Version: 2.4
Name: cars-forge
Version: 1.3.5
Summary: Create an on-demand/spot fleet of single or cluster EC2 instances.
Project-URL: Homepage, https://github.com/carsdotcom/cars-forge/
Project-URL: Documentation, https://carsdotcom.github.io/cars-forge/
Project-URL: Changelog, https://github.com/carsdotcom/cars-forge/blob/main/CHANGELOG.md
Author-email: Nikhil Patel <npatel@cars.com>, Gabriele Ron <gron@cars.com>, Joao Moreira <jmoreira@cars.com>
Maintainer-email: Nikhil Patel <npatel@cars.com>, Gabriele Ron <gron@cars.com>, Joao Moreira <jmoreira@cars.com>
License-Expression: Apache-2.0
License-File: LICENSE
Keywords: AWS,Cluster,EC2,Jupyter,On-Demand,Spark,Spot
Classifier: Development Status :: 5 - Production/Stable
Classifier: Environment :: Console
Classifier: Intended Audience :: Developers
Classifier: License :: OSI Approved :: Apache Software License
Classifier: Natural Language :: English
Classifier: Operating System :: Unix
Classifier: Programming Language :: Python
Classifier: Programming Language :: Python :: 3
Classifier: Programming Language :: Python :: 3.9
Classifier: Programming Language :: Python :: 3.10
Classifier: Programming Language :: Python :: 3.11
Requires-Python: >=3.9
Requires-Dist: boto3
Requires-Dist: pyyaml
Requires-Dist: schema
Provides-Extra: dev
Requires-Dist: bump2version~=1.0; extra == 'dev'
Provides-Extra: test
Requires-Dist: pytest; extra == 'test'
Requires-Dist: pytest-cov; extra == 'test'
